encryptionx/__init__.py
encryptionx/core.py
encryptionx-2.0.0.dist-info/LICENSE
encryptionx-2.0.0.dist-info/METADATA
encryptionx-2.0.0.dist-info/WHEEL
encryptionx-2.0.0.dist-info/top_level.txt
encryptionx-2.0.0.dist-info/RECORD
