Metadata-Version: 2.1
Name: encryptionx
Version: 2.0.0
Summary: A comprehensive encryption library for Python.
Home-page: https://github.com/mr-r0ot/encryptionx
Author: Mohammad Taha Gorji
Author-email: Mohammad Taha Gorji <MohammadTahaGorjiProfile@gmail.com>
License: MIT License
Project-URL: Homepage, https://github.com/mr-r0ot/encryptionx
Requires-Python: >=3.6
License-File: LICENSE
Requires-Dist: pycryptodome
